pitwi/__init__.py
pitwi/binding.py
pitwi/colors.py
pitwi/ids.py
pitwi/keypress.py
pitwi/navigation.py
pitwi/parser.py
pitwi/terminal.py
pitwi/objects/__init__.py
pitwi/objects/border.py
pitwi/objects/button.py
pitwi/objects/carousel.py
pitwi/objects/checkButton.py
pitwi/objects/entry.py
pitwi/objects/map.py
pitwi/objects/menu.py
pitwi/objects/root.py
pitwi/objects/scrolling.py
pitwi/objects/text.py
pitwi/objects/zone.py
pitwi-0.5.2.dist-info/METADATA
pitwi-0.5.2.dist-info/WHEEL
pitwi-0.5.2.dist-info/top_level.txt
pitwi-0.5.2.dist-info/RECORD
