Metadata-Version: 2.1
Name: pitwi
Version: 0.5.2
Summary: User interface for terminal.
Home-page: https://github.com/4surix/pitwi
Author: Asurix
Author-email: asurix@outlook.fr
License: UNKNOWN
Keywords: terminal tui gui console user interface
Platform: UNKNOWN
Classifier: Intended Audience :: Developers
Classifier: Intended Audience :: End Users/Desktop
Classifier: Programming Language :: Python :: 3 :: Only
Classifier: Natural Language :: French
Requires-Python: >=3, <4
